{
  "entity": {
    "entity_type": "source",
    "entity_id": {
      "$type": "oid",
      "$value": "ea3e73e1f20db6e214a6cc5d"
    },
    "entity_name": "testSchemaCrawl"
  },
  "source": {
    "connection": {
      "connection_method": "tpt",
      "connection_string": "jdbc:teradata:\/\/ec2-54-144-76-210.compute-1.amazonaws.com\/TMODE=ANSI,database=dwt_edw",
      "username": "dbc",
      "password": "aW5mb3dvcmtz",
      "schema": "dwt_edw",
      "database": "TERADATA",
      "driver_name": "com.teradata.jdbc.TeraDriver"
    },
    "cdc_mode": "cdc-query",
    "hive_schema": "testSchemaCrawl",
    "sourceType": "rdbms",
    "sourceSubtype": "teradata"
  },
  "tables": [
    {
      "entity_type": "table",
      "entity_id": {
        "$type": "oid",
        "$value": "57c5be1be4b0524ca3cb7893"
      },
      "configuration": {
        "configuration": {
          "hive_table_name": "CAT_ONE_DEMO",
          "sync_type": "cdc-timestamp-column",
          "split_by_key": null,
          "split_by_key_extract_from_col": false,
          "split_by_key_derive_function": "",
          "split_by_key_derive_column": null,
          "chunk_load": {
            "status": "disabled",
            "column": {

            },
            "derive_function": null
          },
          "partition_key": null,
          "partition_key_extract_from_col": false,
          "partition_key_derive_function": "",
          "partition_key_derive_column": null,
          "schema_synchronization_enabled": false,
          "natural_key": [
            "FNAME",
            "LNAME"
          ],
          "timestamp_column_insert": "REC_ADD_TS",
          "timestamp_column_update": "REC_CHG_TS",
          "query_insert": "",
          "query_insert_column": null,
          "query_update": "",
          "query_update_column": null,
          "number_of_mappers": null,
          "number_of_reducers": null,
          "number_of_secondary_partitions": null,
          "number_of_merge_parallel_secondary_partitions": null,
          "number_of_merge_parallel_inmemory_secondary_partitions": null,
          "offset_cdc_start": 0,
          "offset_cdc_end": 0,
          "external_audit_schema": "",
          "external_audit_table": "",
          "external_audit_join_column": "",
          "external_audit_timestamp_column": "",
          "export_enabled": false,
          "export": {

          },
          "tpt_export_writer_instances": 5,
          "tpt_export_reader_instances": 1,
          "tpt_characterset": "UTF8"
        }
      }
    },
    {
      "entity_type": "table",
      "entity_id": {
        "$type": "oid",
        "$value": "57c5be1be4b0524ca3cb789d"
      },
      "configuration": {
        "configuration": {
          "hive_table_name": "CAT_ONE_TEST"
        }
      }
    },
    {
      "entity_type": "table",
      "entity_id": {
        "$type": "oid",
        "$value": "57c5be1be4b0524ca3cb78a7"
      },
      "configuration": {
        "configuration": {
          "hive_table_name": "CAT_TWO_DEMO",
          "sync_type": "cdc-query",
          "split_by_key": null,
          "split_by_key_extract_from_col": false,
          "split_by_key_derive_function": "",
          "split_by_key_derive_column": null,
          "chunk_load": {
            "status": "disabled",
            "column": {

            },
            "derive_function": null
          },
          "partition_key": null,
          "partition_key_extract_from_col": false,
          "partition_key_derive_function": "",
          "partition_key_derive_column": null,
          "schema_synchronization_enabled": false,
          "natural_key": [
            "FNAME",
            "LNAME",
            "REC_HIST_GID"
          ],
          "scd_type": "scd-2",
          "query_insert_enabled": true,
          "query_insert": "SELECT A.*,\n                                          B.rec_add_ts as ZIW_REC_ADD_TS\n                                   FROM   dwt_edw.cat_two_demo A\n                                          JOIN dwt_edw.t_rec_hist B\n                                            ON A.rec_hist_gid = B.rec_hist_gid\n                                   WHERE  prcs_gid IN ( 998877 )\n                                          AND rec_add_ts > Cast(\n                                              cdc_start_time AS\n                                              TIMESTAMP) and rec_add_ts <=Cast(\n                                              cdc_end_time AS\n                                              TIMESTAMP)",
          "query_insert_column": "REC_HIST_GID",
          "query_update_enabled": true,
          "query_update": "SELECT A.*,B.REC_ADD_TS AS ZIW_REC_ADD_TS\n        FROM   dwt_edw.cat_two_demo A\n               INNER JOIN (SELECT TEMP.fname              AS TFNAME,\n                                  TEMP.lname              AS TLNAME,\n                                  ( TEMP.rec_eff_dt - 1 ) AS TREC_EXPRN_DT,\n                                  TEMP.rec_add_ts         AS REC_ADD_TS\n                           FROM   (SELECT C.*,\n                                          D.rec_add_ts\n                                   FROM   dwt_edw.cat_two_demo C\n                                          JOIN dwt_edw.t_rec_hist D\n                                            ON C.rec_hist_gid = D.rec_hist_gid\n                                   WHERE  prcs_gid IN ( 998877 )\n                                          AND rec_add_ts > Cast(\n                                              cdc_start_time AS\n                                              TIMESTAMP) and rec_add_ts <=Cast(\n                                              cdc_end_time AS\n                                              TIMESTAMP)\n                                  ) TEMP) B\n                           ON A.fname = B.tfname\n                          AND A.lname = B.tlname\n                          AND A.rec_exprn_dt = B.trec_exprn_dt\n",
          "number_of_mappers": null,
          "number_of_reducers": null,
          "number_of_secondary_partitions": null,
          "number_of_merge_parallel_secondary_partitions": null,
          "number_of_merge_parallel_inmemory_secondary_partitions": null,
          "offset_cdc_start": 0,
          "offset_cdc_end": 0,
          "external_audit_schema": "DWT_EDW",
          "external_audit_table": "T_REC_HIST",
          "external_audit_join_column": "REC_HIST_GID",
          "external_audit_timestamp_column": "REC_ADD_TS",
          "export_enabled": false,
          "export": {

          },
          "tpt_export_writer_instances": 5,
          "tpt_export_reader_instances": 1,
          "tpt_characterset": "UTF8"
        }
      }
    },
    {
      "entity_type": "table",
      "entity_id": {
        "$type": "oid",
        "$value": "57c5be1be4b0524ca3cb78b1"
      },
      "configuration": {
        "configuration": {
          "hive_table_name": "CAT_TWO_TEST"
        }
      }
    },
    {
      "entity_type": "table",
      "entity_id": {
        "$type": "oid",
        "$value": "57c5be1be4b0524ca3cb78b6"
      },
      "configuration": {
        "configuration": {
          "hive_table_name": "CAT_TWO_Testing"
        }
      }
    },
    {
      "entity_type": "table",
      "entity_id": {
        "$type": "oid",
        "$value": "57c5be1be4b0524ca3cb78ca"
      },
      "configuration": {
        "configuration": {
          "hive_table_name": "PARTITION_TEST"
        }
      }
    },
    {
      "entity_type": "table",
      "entity_id": {
        "$type": "oid",
        "$value": "57c5be1be4b0524ca3cb78de"
      },
      "configuration": {
        "configuration": {
          "hive_table_name": "T20306JD"
        }
      }
    },
    {
      "entity_type": "table",
      "entity_id": {
        "$type": "oid",
        "$value": "57c5be1be4b0524ca3cb78e8"
      },
      "configuration": {
        "configuration": {
          "hive_table_name": "TEST1_err2"
        }
      }
    },
    {
      "entity_type": "table",
      "entity_id": {
        "$type": "oid",
        "$value": "57c5be1ce4b0524ca3cb791a"
      },
      "configuration": {
        "configuration": {
          "hive_table_name": "T_ACCT_PROD"
        }
      }
    },
    {
      "entity_type": "table",
      "entity_id": {
        "$type": "oid",
        "$value": "57c5be1ce4b0524ca3cb791f"
      },
      "configuration": {
        "configuration": {
          "hive_table_name": "T_ADH_EPH_STAR_DRUG_CLS"
        }
      }
    },
    {
      "entity_type": "table",
      "entity_id": {
        "$type": "oid",
        "$value": "57c5be1ce4b0524ca3cb7924"
      },
      "configuration": {
        "configuration": {
          "hive_table_name": "T_ADH_STAR_DRUG_CLS"
        }
      }
    },
    {
      "entity_type": "table",
      "entity_id": {
        "$type": "oid",
        "$value": "57c5be1ce4b0524ca3cb7929"
      },
      "configuration": {
        "configuration": {
          "hive_table_name": "T_CLM_CDD"
        }
      }
    },
    {
      "entity_type": "table",
      "entity_id": {
        "$type": "oid",
        "$value": "57c5be1ce4b0524ca3cb792e"
      },
      "configuration": {
        "configuration": {
          "hive_table_name": "T_CLM_CMPND"
        }
      }
    },
    {
      "entity_type": "table",
      "entity_id": {
        "$type": "oid",
        "$value": "57c5be1ce4b0524ca3cb7933"
      },
      "configuration": {
        "configuration": {
          "hive_table_name": "T_CLM_EGWP_DUAL_DEMO"
        }
      }
    },
    {
      "entity_type": "table",
      "entity_id": {
        "$type": "oid",
        "$value": "57c5be1ce4b0524ca3cb7938"
      },
      "configuration": {
        "configuration": {
          "hive_table_name": "T_CLM_EGWP_DUAL_DEMO_1"
        }
      }
    },
    {
      "entity_type": "table",
      "entity_id": {
        "$type": "oid",
        "$value": "57c5be1ce4b0524ca3cb793d"
      },
      "configuration": {
        "configuration": {
          "hive_table_name": "T_CLM_RJCT"
        }
      }
    },
    {
      "entity_type": "table",
      "entity_id": {
        "$type": "oid",
        "$value": "57c5be1ce4b0524ca3cb7942"
      },
      "configuration": {
        "configuration": {
          "hive_table_name": "T_CLNT_ACCT_CVRG"
        }
      }
    },
    {
      "entity_type": "table",
      "entity_id": {
        "$type": "oid",
        "$value": "57c5be1ce4b0524ca3cb7947"
      },
      "configuration": {
        "configuration": {
          "hive_table_name": "T_CLNT_ACCT_DUAL_DEMO_HIST"
        }
      }
    },
    {
      "entity_type": "table",
      "entity_id": {
        "$type": "oid",
        "$value": "57c5be1ce4b0524ca3cb794c"
      },
      "configuration": {
        "configuration": {
          "hive_table_name": "T_FAKE_PHMCY_CLM"
        }
      }
    },
    {
      "entity_type": "table",
      "entity_id": {
        "$type": "oid",
        "$value": "57c5be1ce4b0524ca3cb7951"
      },
      "configuration": {
        "configuration": {
          "hive_table_name": "T_KPI_STAT"
        }
      }
    },
    {
      "entity_type": "table",
      "entity_id": {
        "$type": "oid",
        "$value": "57c5be1ce4b0524ca3cb7956"
      },
      "configuration": {
        "configuration": {
          "hive_table_name": "T_MBR_ACCT_ADDR"
        }
      }
    },
    {
      "entity_type": "table",
      "entity_id": {
        "$type": "oid",
        "$value": "57c5be1ce4b0524ca3cb795b"
      },
      "configuration": {
        "configuration": {
          "hive_table_name": "T_MBR_ACCT_ADDR_SCNDRY_HIST"
        }
      }
    },
    {
      "entity_type": "table",
      "entity_id": {
        "$type": "oid",
        "$value": "57c5be1ce4b0524ca3cb7960"
      },
      "configuration": {
        "configuration": {
          "hive_table_name": "T_MBR_ACCT_CONT_CVRG_1"
        }
      }
    },
    {
      "entity_type": "table",
      "entity_id": {
        "$type": "oid",
        "$value": "57c5be1ce4b0524ca3cb7965"
      },
      "configuration": {
        "configuration": {
          "hive_table_name": "T_MBR_ACCT_CRFCLTY"
        }
      }
    },
    {
      "entity_type": "table",
      "entity_id": {
        "$type": "oid",
        "$value": "57c5be1ce4b0524ca3cb796a"
      },
      "configuration": {
        "configuration": {
          "hive_table_name": "T_MBR_ACCT_CVRG"
        }
      }
    },
    {
      "entity_type": "table",
      "entity_id": {
        "$type": "oid",
        "$value": "57c5be1ce4b0524ca3cb796f"
      },
      "configuration": {
        "configuration": {
          "hive_table_name": "T_MBR_ACCT_DENORM_2"
        }
      }
    },
    {
      "entity_type": "table",
      "entity_id": {
        "$type": "oid",
        "$value": "57c5be1ce4b0524ca3cb7974"
      },
      "configuration": {
        "configuration": {
          "hive_table_name": "T_MBR_ACCT_GRC_PRD"
        }
      }
    },
    {
      "entity_type": "table",
      "entity_id": {
        "$type": "oid",
        "$value": "57c5be1ce4b0524ca3cb7979"
      },
      "configuration": {
        "configuration": {
          "hive_table_name": "T_MBR_ACCT_HIST"
        }
      }
    },
    {
      "entity_type": "table",
      "entity_id": {
        "$type": "oid",
        "$value": "57c5be1ce4b0524ca3cb797e"
      },
      "configuration": {
        "configuration": {
          "hive_table_name": "T_MBR_ACCT_HRCHY"
        }
      }
    },
    {
      "entity_type": "table",
      "entity_id": {
        "$type": "oid",
        "$value": "57c5be1ce4b0524ca3cb7983"
      },
      "configuration": {
        "configuration": {
          "hive_table_name": "T_MBR_ACCT_MEDD_CVRG"
        }
      }
    },
    {
      "entity_type": "table",
      "entity_id": {
        "$type": "oid",
        "$value": "57c5be1ce4b0524ca3cb7988"
      },
      "configuration": {
        "configuration": {
          "hive_table_name": "T_MBR_ACCT_PGM_CVRG_HIST"
        }
      }
    },
    {
      "entity_type": "table",
      "entity_id": {
        "$type": "oid",
        "$value": "57c5be1ce4b0524ca3cb798d"
      },
      "configuration": {
        "configuration": {
          "hive_table_name": "T_MBR_CMNCN_OPT_HIST"
        }
      }
    },
    {
      "entity_type": "table",
      "entity_id": {
        "$type": "oid",
        "$value": "57c5be1ce4b0524ca3cb7992"
      },
      "configuration": {
        "configuration": {
          "hive_table_name": "T_MBR_FIR_HDR"
        }
      }
    },
    {
      "entity_type": "table",
      "entity_id": {
        "$type": "oid",
        "$value": "57c5be1ce4b0524ca3cb7997"
      },
      "configuration": {
        "configuration": {
          "hive_table_name": "T_MBR_MEDD_ANNL_ENRLM"
        }
      }
    },
    {
      "entity_type": "table",
      "entity_id": {
        "$type": "oid",
        "$value": "57c5be1ce4b0524ca3cb799c"
      },
      "configuration": {
        "configuration": {
          "hive_table_name": "T_MBR_MEDD_CMS_MMDR"
        }
      }
    },
    {
      "entity_type": "table",
      "entity_id": {
        "$type": "oid",
        "$value": "57c5be1ce4b0524ca3cb79a1"
      },
      "configuration": {
        "configuration": {
          "hive_table_name": "T_MBR_MEDD_CMS_TRR"
        }
      }
    },
    {
      "entity_type": "table",
      "entity_id": {
        "$type": "oid",
        "$value": "57c5be1ce4b0524ca3cb79a6"
      },
      "configuration": {
        "configuration": {
          "hive_table_name": "T_MBR_MEDD_LISHIST_DTL"
        }
      }
    },
    {
      "entity_type": "table",
      "entity_id": {
        "$type": "oid",
        "$value": "57c5be1ce4b0524ca3cb79ab"
      },
      "configuration": {
        "configuration": {
          "hive_table_name": "T_MBR_MEDD_LISHIST_DUP"
        }
      }
    },
    {
      "entity_type": "table",
      "entity_id": {
        "$type": "oid",
        "$value": "57c5be1ce4b0524ca3cb79b0"
      },
      "configuration": {
        "configuration": {
          "hive_table_name": "T_MBR_MEDD_LISHIST_EXPLD"
        }
      }
    },
    {
      "entity_type": "table",
      "entity_id": {
        "$type": "oid",
        "$value": "57c5be1ce4b0524ca3cb79b5"
      },
      "configuration": {
        "configuration": {
          "hive_table_name": "T_MBR_MEDD_LISHIST_HDR"
        }
      }
    },
    {
      "entity_type": "table",
      "entity_id": {
        "$type": "oid",
        "$value": "57c5be1ce4b0524ca3cb79ba"
      },
      "configuration": {
        "configuration": {
          "hive_table_name": "T_MBR_MEDD_MOD_DUP"
        }
      }
    },
    {
      "entity_type": "table",
      "entity_id": {
        "$type": "oid",
        "$value": "57c5be1ce4b0524ca3cb79bf"
      },
      "configuration": {
        "configuration": {
          "hive_table_name": "T_MBR_MEDD_MOD_HDR"
        }
      }
    },
    {
      "entity_type": "table",
      "entity_id": {
        "$type": "oid",
        "$value": "57c5be1ce4b0524ca3cb79c4"
      },
      "configuration": {
        "configuration": {
          "hive_table_name": "T_MBR_MEDD_PA_AUDT_TRL"
        }
      }
    },
    {
      "entity_type": "table",
      "entity_id": {
        "$type": "oid",
        "$value": "57c5be1ce4b0524ca3cb79c9"
      },
      "configuration": {
        "configuration": {
          "hive_table_name": "T_MBR_MEDD_PA_NOTES"
        }
      }
    },
    {
      "entity_type": "table",
      "entity_id": {
        "$type": "oid",
        "$value": "57c5be1ce4b0524ca3cb79ce"
      },
      "configuration": {
        "configuration": {
          "hive_table_name": "T_MEDD_FRMLY_RFRNC_FILE"
        }
      }
    },
    {
      "entity_type": "table",
      "entity_id": {
        "$type": "oid",
        "$value": "57c5be1ce4b0524ca3cb79d3"
      },
      "configuration": {
        "configuration": {
          "hive_table_name": "T_MEDD_MBR_ADJ_DTL"
        }
      }
    },
    {
      "entity_type": "table",
      "entity_id": {
        "$type": "oid",
        "$value": "57c5be1ce4b0524ca3cb79d8"
      },
      "configuration": {
        "configuration": {
          "hive_table_name": "T_MEDD_PHMCY_CMS_SBMSN_CLNDR"
        }
      }
    },
    {
      "entity_type": "table",
      "entity_id": {
        "$type": "oid",
        "$value": "57c5be1ce4b0524ca3cb79dd"
      },
      "configuration": {
        "configuration": {
          "hive_table_name": "T_MEDD_PHMCY_COST_HDR"
        }
      }
    },
    {
      "entity_type": "table",
      "entity_id": {
        "$type": "oid",
        "$value": "57c5be1ce4b0524ca3cb79e2"
      },
      "configuration": {
        "configuration": {
          "hive_table_name": "T_MEDD_PHMCY_COST_XWALK"
        }
      }
    },
    {
      "entity_type": "table",
      "entity_id": {
        "$type": "oid",
        "$value": "57c5be1ce4b0524ca3cb79e7"
      },
      "configuration": {
        "configuration": {
          "hive_table_name": "T_MEDD_PHMCY_PRC"
        }
      }
    },
    {
      "entity_type": "table",
      "entity_id": {
        "$type": "oid",
        "$value": "57c5be1ce4b0524ca3cb79ec"
      },
      "configuration": {
        "configuration": {
          "hive_table_name": "T_MEDD_PHMCY_PRC_HDR"
        }
      }
    },
    {
      "entity_type": "table",
      "entity_id": {
        "$type": "oid",
        "$value": "57c5be1ce4b0524ca3cb79f1"
      },
      "configuration": {
        "configuration": {
          "hive_table_name": "T_MEDD_PHMCY_PRC_HIST"
        }
      }
    },
    {
      "entity_type": "table",
      "entity_id": {
        "$type": "oid",
        "$value": "57c5be1de4b0524ca3cb79f6"
      },
      "configuration": {
        "configuration": {
          "hive_table_name": "T_MEDD_PHMCY_PRC_XWALK"
        }
      }
    },
    {
      "entity_type": "table",
      "entity_id": {
        "$type": "oid",
        "$value": "57c5be1de4b0524ca3cb79fb"
      },
      "configuration": {
        "configuration": {
          "hive_table_name": "T_MEDD_PUF_BNFCY_COST"
        }
      }
    },
    {
      "entity_type": "table",
      "entity_id": {
        "$type": "oid",
        "$value": "57c5be1de4b0524ca3cb7a00"
      },
      "configuration": {
        "configuration": {
          "hive_table_name": "T_MEDD_PUF_FRMLY"
        }
      }
    },
    {
      "entity_type": "table",
      "entity_id": {
        "$type": "oid",
        "$value": "57c5be1de4b0524ca3cb7a05"
      },
      "configuration": {
        "configuration": {
          "hive_table_name": "T_MEDD_PUF_FRMLY_EXCL"
        }
      }
    },
    {
      "entity_type": "table",
      "entity_id": {
        "$type": "oid",
        "$value": "57c5be1de4b0524ca3cb7a0a"
      },
      "configuration": {
        "configuration": {
          "hive_table_name": "T_MEDD_PUF_GRPHC_LCTR"
        }
      }
    },
    {
      "entity_type": "table",
      "entity_id": {
        "$type": "oid",
        "$value": "57c5be1de4b0524ca3cb7a0f"
      },
      "configuration": {
        "configuration": {
          "hive_table_name": "T_MEDD_PUF_PARTL_GAP_CVRG"
        }
      }
    },
    {
      "entity_type": "table",
      "entity_id": {
        "$type": "oid",
        "$value": "57c5be1de4b0524ca3cb7a14"
      },
      "configuration": {
        "configuration": {
          "hive_table_name": "T_MEDD_PUF_PHMCY_NTWRK"
        }
      }
    },
    {
      "entity_type": "table",
      "entity_id": {
        "$type": "oid",
        "$value": "57c5be1de4b0524ca3cb7a19"
      },
      "configuration": {
        "configuration": {
          "hive_table_name": "T_MEDD_PUF_PLAN"
        }
      }
    },
    {
      "entity_type": "table",
      "entity_id": {
        "$type": "oid",
        "$value": "57c5be1de4b0524ca3cb7a1e"
      },
      "configuration": {
        "configuration": {
          "hive_table_name": "T_PDE_BTCH_HDR_TRLR_DTL"
        }
      }
    },
    {
      "entity_type": "table",
      "entity_id": {
        "$type": "oid",
        "$value": "57c5be1de4b0524ca3cb7a23"
      },
      "configuration": {
        "configuration": {
          "hive_table_name": "T_PDE_DTL"
        }
      }
    },
    {
      "entity_type": "table",
      "entity_id": {
        "$type": "oid",
        "$value": "57c5be1de4b0524ca3cb7a28"
      },
      "configuration": {
        "configuration": {
          "hive_table_name": "T_PDE_RTRCT"
        }
      }
    },
    {
      "entity_type": "table",
      "entity_id": {
        "$type": "oid",
        "$value": "57c5be1de4b0524ca3cb7a2d"
      },
      "configuration": {
        "configuration": {
          "hive_table_name": "T_PHMCY_CLM"
        }
      }
    },
    {
      "entity_type": "table",
      "entity_id": {
        "$type": "oid",
        "$value": "57c5be1de4b0524ca3cb7a32"
      },
      "configuration": {
        "configuration": {
          "hive_table_name": "T_PHMCY_CLM_ENTPR_TF_TOC"
        }
      }
    },
    {
      "entity_type": "table",
      "entity_id": {
        "$type": "oid",
        "$value": "57c5be1de4b0524ca3cb7a37"
      },
      "configuration": {
        "configuration": {
          "hive_table_name": "T_PHMCY_CLM_TF_LTR_MAIL_DT"
        }
      }
    },
    {
      "entity_type": "table",
      "entity_id": {
        "$type": "oid",
        "$value": "57c5be1de4b0524ca3cb7a3c"
      },
      "configuration": {
        "configuration": {
          "hive_table_name": "T_PHMCY_HIST"
        }
      }
    },
    {
      "entity_type": "table",
      "entity_id": {
        "$type": "oid",
        "$value": "57c5be1de4b0524ca3cb7a41"
      },
      "configuration": {
        "configuration": {
          "hive_table_name": "T_PROD"
        }
      }
    },
    {
      "entity_type": "table",
      "entity_id": {
        "$type": "oid",
        "$value": "57c5be1de4b0524ca3cb7a46"
      },
      "configuration": {
        "configuration": {
          "hive_table_name": "T_PRSCBR_FCLTY_HIST"
        }
      }
    },
    {
      "entity_type": "table",
      "entity_id": {
        "$type": "oid",
        "$value": "57c5be1de4b0524ca3cb7a4b"
      },
      "configuration": {
        "configuration": {
          "hive_table_name": "T_PRSCBR_ST_LIC"
        }
      }
    },
    {
      "entity_type": "table",
      "entity_id": {
        "$type": "oid",
        "$value": "57c5be1de4b0524ca3cb7a50"
      },
      "configuration": {
        "configuration": {
          "hive_table_name": "T_REC_HIST"
        }
      }
    },
    {
      "entity_type": "table",
      "entity_id": {
        "$type": "oid",
        "$value": "57c5be1de4b0524ca3cb7a55"
      },
      "configuration": {
        "configuration": {
          "hive_table_name": "T_RXC_PRIOR_ATHZN"
        }
      }
    },
    {
      "entity_type": "table",
      "entity_id": {
        "$type": "oid",
        "$value": "57c5be1de4b0524ca3cb7a5a"
      },
      "configuration": {
        "configuration": {
          "hive_table_name": "T_SPEC_DRUG"
        }
      }
    },
    {
      "entity_type": "table",
      "entity_id": {
        "$type": "oid",
        "$value": "57c5be1de4b0524ca3cb7a5f"
      },
      "configuration": {
        "configuration": {
          "hive_table_name": "T_USRVW_CLNT_LST"
        }
      }
    },
    {
      "entity_type": "table",
      "entity_id": {
        "$type": "oid",
        "$value": "57c5be1de4b0524ca3cb7a64"
      },
      "configuration": {
        "configuration": {
          "hive_table_name": "T_ZIP5"
        }
      }
    },
    {
      "entity_type": "table",
      "entity_id": {
        "$type": "oid",
        "$value": "57c5be1be4b0524ca3cb787a"
      },
      "configuration": {
        "configuration": {
          "hive_table_name": "big_table_one_ET"
        }
      }
    },
    {
      "entity_type": "table",
      "entity_id": {
        "$type": "oid",
        "$value": "57c5be1be4b0524ca3cb787f"
      },
      "configuration": {
        "configuration": {
          "hive_table_name": "big_table_one_Log"
        }
      }
    },
    {
      "entity_type": "table",
      "entity_id": {
        "$type": "oid",
        "$value": "57c5be1be4b0524ca3cb7884"
      },
      "configuration": {
        "configuration": {
          "hive_table_name": "big_table_one_UV"
        }
      }
    },
    {
      "entity_type": "table",
      "entity_id": {
        "$type": "oid",
        "$value": "57c5be1be4b0524ca3cb7889"
      },
      "configuration": {
        "configuration": {
          "hive_table_name": "big_table_one_WT"
        }
      }
    },
    {
      "entity_type": "table",
      "entity_id": {
        "$type": "oid",
        "$value": "57c5be1be4b0524ca3cb788e"
      },
      "configuration": {
        "configuration": {
          "hive_table_name": "blob_unicode"
        }
      }
    },
    {
      "entity_type": "table",
      "entity_id": {
        "$type": "oid",
        "$value": "57c5be1be4b0524ca3cb7898"
      },
      "configuration": {
        "configuration": {
          "hive_table_name": "cat_one_demo_test"
        }
      }
    },
    {
      "entity_type": "table",
      "entity_id": {
        "$type": "oid",
        "$value": "57c5be1be4b0524ca3cb78a2"
      },
      "configuration": {
        "configuration": {
          "hive_table_name": "cat_one_test_new"
        }
      }
    },
    {
      "entity_type": "table",
      "entity_id": {
        "$type": "oid",
        "$value": "57c5be1be4b0524ca3cb78ac"
      },
      "configuration": {
        "configuration": {
          "hive_table_name": "cat_two_scd1_both",
          "sync_type": "cdc-query",
          "split_by_key": null,
          "split_by_key_extract_from_col": false,
          "split_by_key_derive_function": "",
          "split_by_key_derive_column": null,
          "chunk_load": {
            "status": "disabled",
            "column": {

            },
            "derive_function": null
          },
          "partition_key": null,
          "partition_key_extract_from_col": false,
          "partition_key_derive_function": "",
          "partition_key_derive_column": null,
          "schema_synchronization_enabled": false,
          "natural_key": [
            "FNAME",
            "REC_HIST_GID"
          ],
          "scd_type": "scd-1",
          "query_insert_enabled": true,
          "query_insert": "SELECT A.*,B.rec_add_ts as ZIW_REC_ADD_TS\n                                   FROM   DWT_EDW.CAT_TWO_SCD1_BOTH A\n                                          JOIN t_rec_hist B\n                                            ON A.rec_hist_gid = B.rec_hist_gid\n                                   WHERE  B.rec_add_ts > Cast(\n                                              cdc_start_time AS\n                                              TIMESTAMP) AND B.rec_add_ts <= Cast(\n                                              cdc_end_time AS\n                                              TIMESTAMP)",
          "query_insert_column": "REC_HIST_GID",
          "query_update_enabled": true,
          "query_update": " SELECT A.*,B.rec_add_ts as ZIW_REC_ADD_TS\n                                   FROM   DWT_EDW.CAT_TWO_SCD1_BOTH A\n                                          JOIN DWT_EDW.t_rec_hist B\n                                            ON A.rec_upd_hist_gid = B.rec_hist_gid\n                                   WHERE  prcs_gid IN ( 998877 )\n                                          AND rec_add_ts > Cast(\n                                              cdc_start_time AS\n                                              TIMESTAMP) AND rec_add_ts <= Cast(\n                                              cdc_end_time AS\n                                              TIMESTAMP)",
          "query_update_column": "REC_UPD_HIST_GID",
          "number_of_mappers": null,
          "number_of_reducers": null,
          "number_of_secondary_partitions": null,
          "number_of_merge_parallel_secondary_partitions": null,
          "number_of_merge_parallel_inmemory_secondary_partitions": null,
          "offset_cdc_start": 0,
          "offset_cdc_end": 0,
          "external_audit_schema": "DWT_EDW",
          "external_audit_table": "T_REC_HIST",
          "external_audit_join_column": "REC_HIST_GID",
          "external_audit_timestamp_column": "REC_ADD_TS",
          "export_enabled": false,
          "export": {

          },
          "tpt_export_writer_instances": 5,
          "tpt_export_reader_instances": 1,
          "tpt_characterset": "UTF8"
        }
      }
    },
    {
      "entity_type": "table",
      "entity_id": {
        "$type": "oid",
        "$value": "57c5be1be4b0524ca3cb78bb"
      },
      "configuration": {
        "configuration": {
          "hive_table_name": "customer_success"
        }
      }
    },
    {
      "entity_type": "table",
      "entity_id": {
        "$type": "oid",
        "$value": "57c5be1be4b0524ca3cb78c0"
      },
      "configuration": {
        "configuration": {
          "hive_table_name": "full_export"
        }
      }
    },
    {
      "entity_type": "table",
      "entity_id": {
        "$type": "oid",
        "$value": "57c5be1be4b0524ca3cb78c5"
      },
      "configuration": {
        "configuration": {
          "hive_table_name": "incr_export"
        }
      }
    },
    {
      "entity_type": "table",
      "entity_id": {
        "$type": "oid",
        "$value": "57c5be1be4b0524ca3cb78cf"
      },
      "configuration": {
        "configuration": {
          "hive_table_name": "schema_change_test"
        }
      }
    },
    {
      "entity_type": "table",
      "entity_id": {
        "$type": "oid",
        "$value": "57c5be1be4b0524ca3cb78d4"
      },
      "configuration": {
        "configuration": {
          "hive_table_name": "special_case_test"
        }
      }
    },
    {
      "entity_type": "table",
      "entity_id": {
        "$type": "oid",
        "$value": "57c5be1be4b0524ca3cb78d9"
      },
      "configuration": {
        "configuration": {
          "hive_table_name": "splchars"
        }
      }
    },
    {
      "entity_type": "table",
      "entity_id": {
        "$type": "oid",
        "$value": "57c5be1be4b0524ca3cb78e3"
      },
      "configuration": {
        "configuration": {
          "hive_table_name": "temp_customer_success"
        }
      }
    },
    {
      "entity_type": "table",
      "entity_id": {
        "$type": "oid",
        "$value": "57c5be1be4b0524ca3cb78ed"
      },
      "configuration": {
        "configuration": {
          "hive_table_name": "testJoin"
        }
      }
    },
    {
      "entity_type": "table",
      "entity_id": {
        "$type": "oid",
        "$value": "57c5be1be4b0524ca3cb78fc"
      },
      "configuration": {
        "configuration": {
          "hive_table_name": "testTPT"
        }
      }
    },
    {
      "entity_type": "table",
      "entity_id": {
        "$type": "oid",
        "$value": "57c5be1be4b0524ca3cb7901"
      },
      "configuration": {
        "configuration": {
          "hive_table_name": "test_dattypes_numeric"
        }
      }
    },
    {
      "entity_type": "table",
      "entity_id": {
        "$type": "oid",
        "$value": "57c5be1ce4b0524ca3cb7906"
      },
      "configuration": {
        "configuration": {
          "hive_table_name": "test_delim_escape_tbl"
        }
      }
    },
    {
      "entity_type": "table",
      "entity_id": {
        "$type": "oid",
        "$value": "57c5be1ce4b0524ca3cb790b"
      },
      "configuration": {
        "configuration": {
          "hive_table_name": "test_schema"
        }
      }
    },
    {
      "entity_type": "table",
      "entity_id": {
        "$type": "oid",
        "$value": "57c5be1be4b0524ca3cb78f2"
      },
      "configuration": {
        "configuration": {
          "hive_table_name": "testtable2"
        }
      }
    },
    {
      "entity_type": "table",
      "entity_id": {
        "$type": "oid",
        "$value": "57c5be1be4b0524ca3cb78f7"
      },
      "configuration": {
        "configuration": {
          "hive_table_name": "testtable3"
        }
      }
    },
    {
      "entity_type": "table",
      "entity_id": {
        "$type": "oid",
        "$value": "57c5be1ce4b0524ca3cb7910"
      },
      "configuration": {
        "configuration": {
          "hive_table_name": "tpt_keywords"
        }
      }
    },
    {
      "entity_type": "table",
      "entity_id": {
        "$type": "oid",
        "$value": "57c5be1ce4b0524ca3cb7915"
      },
      "configuration": {
        "configuration": {
          "hive_table_name": "twocols"
        }
      }
    },
    {
      "entity_type": "table",
      "entity_id": {
        "$type": "oid",
        "$value": "57c5be1de4b0524ca3cb7a69"
      },
      "configuration": {
        "configuration": {
          "hive_table_name": "unicode_test",
          "sync_type": "full-load",
          "split_by_key": null,
          "split_by_key_extract_from_col": false,
          "split_by_key_derive_function": "",
          "split_by_key_derive_column": null,
          "chunk_load": {
            "status": "disabled",
            "column": {

            },
            "derive_function": null
          },
          "partition_key": null,
          "partition_key_extract_from_col": false,
          "partition_key_derive_function": "",
          "partition_key_derive_column": null,
          "natural_key": [

          ],
          "query_insert": "",
          "query_insert_column": null,
          "query_update": "",
          "query_update_column": null,
          "number_of_mappers": null,
          "number_of_reducers": null,
          "number_of_secondary_partitions": null,
          "number_of_merge_parallel_secondary_partitions": null,
          "number_of_merge_parallel_inmemory_secondary_partitions": null,
          "offset_cdc_start": 0,
          "offset_cdc_end": 0,
          "export_enabled": false,
          "export": {

          },
          "tpt_export_writer_instances": 5,
          "tpt_export_reader_instances": 1,
          "tpt_characterset": "UTF8"
        }
      }
    },
    {
      "entity_type": "table",
      "entity_id": {
        "$type": "oid",
        "$value": "57c5be1de4b0524ca3cb7a6e"
      },
      "configuration": {
        "configuration": {
          "hive_table_name": "utillog1"
        }
      }
    },
    {
      "entity_type": "table",
      "entity_id": {
        "$type": "oid",
        "$value": "57c5be1de4b0524ca3cb7a73"
      },
      "configuration": {
        "configuration": {
          "hive_table_name": "utillog2"
        }
      }
    },
    {
      "entity_type": "table",
      "entity_id": {
        "$type": "oid",
        "$value": "57c5be1de4b0524ca3cb7a78"
      },
      "configuration": {
        "configuration": {
          "hive_table_name": "utillog6"
        }
      }
    },
    {
      "entity_type": "table",
      "entity_id": {
        "$type": "oid",
        "$value": "57c5be1de4b0524ca3cb7a7d"
      },
      "configuration": {
        "configuration": {
          "hive_table_name": "vw_1_cat_one_test"
        }
      }
    },
    {
      "entity_type": "table",
      "entity_id": {
        "$type": "oid",
        "$value": "57c5be1de4b0524ca3cb7a82"
      },
      "configuration": {
        "configuration": {
          "hive_table_name": "vw_cat_one_test"
        }
      }
    }
  ],
  "table_groups": [
    {
      "entity_type": "table_group",
      "entity_id": {
        "$type": "oid",
        "$value": "d6ab257953a9ec04ad6813f3"
      },
      "configuration": {
        "name": "all",
        "tables": [
          {
            "$type": "oid",
            "$value": "57c5be1be4b0524ca3cb7893"
          },
          {
            "$type": "oid",
            "$value": "57c5be1be4b0524ca3cb78a7"
          },
          {
            "$type": "oid",
            "$value": "57c5be1be4b0524ca3cb78ac"
          },
          {
            "$type": "oid",
            "$value": "57c5be1de4b0524ca3cb7a69"
          }
        ],
        "scheduling": "none",
        "combined_schedule": {

        },
        "cdc_schedule": {

        },
        "merge_schedule": {

        },
        "fullload_schedule": {

        },
        "data_expiry_schedule": {
          "schedule_status": "disabled"
        },
        "source": {
          "$type": "oid",
          "$value": "ea3e73e1f20db6e214a6cc5d"
        },
        "yarn_queue": ""
      }
    }
  ],
  "iw_mappings": [
    {
      "entity_type": "source",
      "entity_id": {
        "$type": "oid",
        "$value": "ea3e73e1f20db6e214a6cc5d"
      },
      "recommendation": {
        "source_name": "testSchemaCrawl"
      }
    },
    {
      "entity_type": "table",
      "entity_id": {
        "$type": "oid",
        "$value": "57c5be1be4b0524ca3cb7893"
      },
      "recommendation": {
        "table_name": "CAT_ONE_DEMO"
      }
    },
    {
      "entity_type": "table",
      "entity_id": {
        "$type": "oid",
        "$value": "57c5be1be4b0524ca3cb789d"
      },
      "recommendation": {
        "table_name": "CAT_ONE_TEST"
      }
    },
    {
      "entity_type": "table",
      "entity_id": {
        "$type": "oid",
        "$value": "57c5be1be4b0524ca3cb78a7"
      },
      "recommendation": {
        "table_name": "CAT_TWO_DEMO"
      }
    },
    {
      "entity_type": "table",
      "entity_id": {
        "$type": "oid",
        "$value": "57c5be1be4b0524ca3cb78b1"
      },
      "recommendation": {
        "table_name": "CAT_TWO_TEST"
      }
    },
    {
      "entity_type": "table",
      "entity_id": {
        "$type": "oid",
        "$value": "57c5be1be4b0524ca3cb78b6"
      },
      "recommendation": {
        "table_name": "CAT_TWO_Testing"
      }
    },
    {
      "entity_type": "table",
      "entity_id": {
        "$type": "oid",
        "$value": "57c5be1be4b0524ca3cb78ca"
      },
      "recommendation": {
        "table_name": "PARTITION_TEST"
      }
    },
    {
      "entity_type": "table",
      "entity_id": {
        "$type": "oid",
        "$value": "57c5be1be4b0524ca3cb78de"
      },
      "recommendation": {
        "table_name": "T20306JD"
      }
    },
    {
      "entity_type": "table",
      "entity_id": {
        "$type": "oid",
        "$value": "57c5be1be4b0524ca3cb78e8"
      },
      "recommendation": {
        "table_name": "TEST1_err2"
      }
    },
    {
      "entity_type": "table",
      "entity_id": {
        "$type": "oid",
        "$value": "57c5be1ce4b0524ca3cb791a"
      },
      "recommendation": {
        "table_name": "T_ACCT_PROD"
      }
    },
    {
      "entity_type": "table",
      "entity_id": {
        "$type": "oid",
        "$value": "57c5be1ce4b0524ca3cb791f"
      },
      "recommendation": {
        "table_name": "T_ADH_EPH_STAR_DRUG_CLS"
      }
    },
    {
      "entity_type": "table",
      "entity_id": {
        "$type": "oid",
        "$value": "57c5be1ce4b0524ca3cb7924"
      },
      "recommendation": {
        "table_name": "T_ADH_STAR_DRUG_CLS"
      }
    },
    {
      "entity_type": "table",
      "entity_id": {
        "$type": "oid",
        "$value": "57c5be1ce4b0524ca3cb7929"
      },
      "recommendation": {
        "table_name": "T_CLM_CDD"
      }
    },
    {
      "entity_type": "table",
      "entity_id": {
        "$type": "oid",
        "$value": "57c5be1ce4b0524ca3cb792e"
      },
      "recommendation": {
        "table_name": "T_CLM_CMPND"
      }
    },
    {
      "entity_type": "table",
      "entity_id": {
        "$type": "oid",
        "$value": "57c5be1ce4b0524ca3cb7933"
      },
      "recommendation": {
        "table_name": "T_CLM_EGWP_DUAL_DEMO"
      }
    },
    {
      "entity_type": "table",
      "entity_id": {
        "$type": "oid",
        "$value": "57c5be1ce4b0524ca3cb7938"
      },
      "recommendation": {
        "table_name": "T_CLM_EGWP_DUAL_DEMO_1"
      }
    },
    {
      "entity_type": "table",
      "entity_id": {
        "$type": "oid",
        "$value": "57c5be1ce4b0524ca3cb793d"
      },
      "recommendation": {
        "table_name": "T_CLM_RJCT"
      }
    },
    {
      "entity_type": "table",
      "entity_id": {
        "$type": "oid",
        "$value": "57c5be1ce4b0524ca3cb7942"
      },
      "recommendation": {
        "table_name": "T_CLNT_ACCT_CVRG"
      }
    },
    {
      "entity_type": "table",
      "entity_id": {
        "$type": "oid",
        "$value": "57c5be1ce4b0524ca3cb7947"
      },
      "recommendation": {
        "table_name": "T_CLNT_ACCT_DUAL_DEMO_HIST"
      }
    },
    {
      "entity_type": "table",
      "entity_id": {
        "$type": "oid",
        "$value": "57c5be1ce4b0524ca3cb794c"
      },
      "recommendation": {
        "table_name": "T_FAKE_PHMCY_CLM"
      }
    },
    {
      "entity_type": "table",
      "entity_id": {
        "$type": "oid",
        "$value": "57c5be1ce4b0524ca3cb7951"
      },
      "recommendation": {
        "table_name": "T_KPI_STAT"
      }
    },
    {
      "entity_type": "table",
      "entity_id": {
        "$type": "oid",
        "$value": "57c5be1ce4b0524ca3cb7956"
      },
      "recommendation": {
        "table_name": "T_MBR_ACCT_ADDR"
      }
    },
    {
      "entity_type": "table",
      "entity_id": {
        "$type": "oid",
        "$value": "57c5be1ce4b0524ca3cb795b"
      },
      "recommendation": {
        "table_name": "T_MBR_ACCT_ADDR_SCNDRY_HIST"
      }
    },
    {
      "entity_type": "table",
      "entity_id": {
        "$type": "oid",
        "$value": "57c5be1ce4b0524ca3cb7960"
      },
      "recommendation": {
        "table_name": "T_MBR_ACCT_CONT_CVRG_1"
      }
    },
    {
      "entity_type": "table",
      "entity_id": {
        "$type": "oid",
        "$value": "57c5be1ce4b0524ca3cb7965"
      },
      "recommendation": {
        "table_name": "T_MBR_ACCT_CRFCLTY"
      }
    },
    {
      "entity_type": "table",
      "entity_id": {
        "$type": "oid",
        "$value": "57c5be1ce4b0524ca3cb796a"
      },
      "recommendation": {
        "table_name": "T_MBR_ACCT_CVRG"
      }
    },
    {
      "entity_type": "table",
      "entity_id": {
        "$type": "oid",
        "$value": "57c5be1ce4b0524ca3cb796f"
      },
      "recommendation": {
        "table_name": "T_MBR_ACCT_DENORM_2"
      }
    },
    {
      "entity_type": "table",
      "entity_id": {
        "$type": "oid",
        "$value": "57c5be1ce4b0524ca3cb7974"
      },
      "recommendation": {
        "table_name": "T_MBR_ACCT_GRC_PRD"
      }
    },
    {
      "entity_type": "table",
      "entity_id": {
        "$type": "oid",
        "$value": "57c5be1ce4b0524ca3cb7979"
      },
      "recommendation": {
        "table_name": "T_MBR_ACCT_HIST"
      }
    },
    {
      "entity_type": "table",
      "entity_id": {
        "$type": "oid",
        "$value": "57c5be1ce4b0524ca3cb797e"
      },
      "recommendation": {
        "table_name": "T_MBR_ACCT_HRCHY"
      }
    },
    {
      "entity_type": "table",
      "entity_id": {
        "$type": "oid",
        "$value": "57c5be1ce4b0524ca3cb7983"
      },
      "recommendation": {
        "table_name": "T_MBR_ACCT_MEDD_CVRG"
      }
    },
    {
      "entity_type": "table",
      "entity_id": {
        "$type": "oid",
        "$value": "57c5be1ce4b0524ca3cb7988"
      },
      "recommendation": {
        "table_name": "T_MBR_ACCT_PGM_CVRG_HIST"
      }
    },
    {
      "entity_type": "table",
      "entity_id": {
        "$type": "oid",
        "$value": "57c5be1ce4b0524ca3cb798d"
      },
      "recommendation": {
        "table_name": "T_MBR_CMNCN_OPT_HIST"
      }
    },
    {
      "entity_type": "table",
      "entity_id": {
        "$type": "oid",
        "$value": "57c5be1ce4b0524ca3cb7992"
      },
      "recommendation": {
        "table_name": "T_MBR_FIR_HDR"
      }
    },
    {
      "entity_type": "table",
      "entity_id": {
        "$type": "oid",
        "$value": "57c5be1ce4b0524ca3cb7997"
      },
      "recommendation": {
        "table_name": "T_MBR_MEDD_ANNL_ENRLM"
      }
    },
    {
      "entity_type": "table",
      "entity_id": {
        "$type": "oid",
        "$value": "57c5be1ce4b0524ca3cb799c"
      },
      "recommendation": {
        "table_name": "T_MBR_MEDD_CMS_MMDR"
      }
    },
    {
      "entity_type": "table",
      "entity_id": {
        "$type": "oid",
        "$value": "57c5be1ce4b0524ca3cb79a1"
      },
      "recommendation": {
        "table_name": "T_MBR_MEDD_CMS_TRR"
      }
    },
    {
      "entity_type": "table",
      "entity_id": {
        "$type": "oid",
        "$value": "57c5be1ce4b0524ca3cb79a6"
      },
      "recommendation": {
        "table_name": "T_MBR_MEDD_LISHIST_DTL"
      }
    },
    {
      "entity_type": "table",
      "entity_id": {
        "$type": "oid",
        "$value": "57c5be1ce4b0524ca3cb79ab"
      },
      "recommendation": {
        "table_name": "T_MBR_MEDD_LISHIST_DUP"
      }
    },
    {
      "entity_type": "table",
      "entity_id": {
        "$type": "oid",
        "$value": "57c5be1ce4b0524ca3cb79b0"
      },
      "recommendation": {
        "table_name": "T_MBR_MEDD_LISHIST_EXPLD"
      }
    },
    {
      "entity_type": "table",
      "entity_id": {
        "$type": "oid",
        "$value": "57c5be1ce4b0524ca3cb79b5"
      },
      "recommendation": {
        "table_name": "T_MBR_MEDD_LISHIST_HDR"
      }
    },
    {
      "entity_type": "table",
      "entity_id": {
        "$type": "oid",
        "$value": "57c5be1ce4b0524ca3cb79ba"
      },
      "recommendation": {
        "table_name": "T_MBR_MEDD_MOD_DUP"
      }
    },
    {
      "entity_type": "table",
      "entity_id": {
        "$type": "oid",
        "$value": "57c5be1ce4b0524ca3cb79bf"
      },
      "recommendation": {
        "table_name": "T_MBR_MEDD_MOD_HDR"
      }
    },
    {
      "entity_type": "table",
      "entity_id": {
        "$type": "oid",
        "$value": "57c5be1ce4b0524ca3cb79c4"
      },
      "recommendation": {
        "table_name": "T_MBR_MEDD_PA_AUDT_TRL"
      }
    },
    {
      "entity_type": "table",
      "entity_id": {
        "$type": "oid",
        "$value": "57c5be1ce4b0524ca3cb79c9"
      },
      "recommendation": {
        "table_name": "T_MBR_MEDD_PA_NOTES"
      }
    },
    {
      "entity_type": "table",
      "entity_id": {
        "$type": "oid",
        "$value": "57c5be1ce4b0524ca3cb79ce"
      },
      "recommendation": {
        "table_name": "T_MEDD_FRMLY_RFRNC_FILE"
      }
    },
    {
      "entity_type": "table",
      "entity_id": {
        "$type": "oid",
        "$value": "57c5be1ce4b0524ca3cb79d3"
      },
      "recommendation": {
        "table_name": "T_MEDD_MBR_ADJ_DTL"
      }
    },
    {
      "entity_type": "table",
      "entity_id": {
        "$type": "oid",
        "$value": "57c5be1ce4b0524ca3cb79d8"
      },
      "recommendation": {
        "table_name": "T_MEDD_PHMCY_CMS_SBMSN_CLNDR"
      }
    },
    {
      "entity_type": "table",
      "entity_id": {
        "$type": "oid",
        "$value": "57c5be1ce4b0524ca3cb79dd"
      },
      "recommendation": {
        "table_name": "T_MEDD_PHMCY_COST_HDR"
      }
    },
    {
      "entity_type": "table",
      "entity_id": {
        "$type": "oid",
        "$value": "57c5be1ce4b0524ca3cb79e2"
      },
      "recommendation": {
        "table_name": "T_MEDD_PHMCY_COST_XWALK"
      }
    },
    {
      "entity_type": "table",
      "entity_id": {
        "$type": "oid",
        "$value": "57c5be1ce4b0524ca3cb79e7"
      },
      "recommendation": {
        "table_name": "T_MEDD_PHMCY_PRC"
      }
    },
    {
      "entity_type": "table",
      "entity_id": {
        "$type": "oid",
        "$value": "57c5be1ce4b0524ca3cb79ec"
      },
      "recommendation": {
        "table_name": "T_MEDD_PHMCY_PRC_HDR"
      }
    },
    {
      "entity_type": "table",
      "entity_id": {
        "$type": "oid",
        "$value": "57c5be1ce4b0524ca3cb79f1"
      },
      "recommendation": {
        "table_name": "T_MEDD_PHMCY_PRC_HIST"
      }
    },
    {
      "entity_type": "table",
      "entity_id": {
        "$type": "oid",
        "$value": "57c5be1de4b0524ca3cb79f6"
      },
      "recommendation": {
        "table_name": "T_MEDD_PHMCY_PRC_XWALK"
      }
    },
    {
      "entity_type": "table",
      "entity_id": {
        "$type": "oid",
        "$value": "57c5be1de4b0524ca3cb79fb"
      },
      "recommendation": {
        "table_name": "T_MEDD_PUF_BNFCY_COST"
      }
    },
    {
      "entity_type": "table",
      "entity_id": {
        "$type": "oid",
        "$value": "57c5be1de4b0524ca3cb7a00"
      },
      "recommendation": {
        "table_name": "T_MEDD_PUF_FRMLY"
      }
    },
    {
      "entity_type": "table",
      "entity_id": {
        "$type": "oid",
        "$value": "57c5be1de4b0524ca3cb7a05"
      },
      "recommendation": {
        "table_name": "T_MEDD_PUF_FRMLY_EXCL"
      }
    },
    {
      "entity_type": "table",
      "entity_id": {
        "$type": "oid",
        "$value": "57c5be1de4b0524ca3cb7a0a"
      },
      "recommendation": {
        "table_name": "T_MEDD_PUF_GRPHC_LCTR"
      }
    },
    {
      "entity_type": "table",
      "entity_id": {
        "$type": "oid",
        "$value": "57c5be1de4b0524ca3cb7a0f"
      },
      "recommendation": {
        "table_name": "T_MEDD_PUF_PARTL_GAP_CVRG"
      }
    },
    {
      "entity_type": "table",
      "entity_id": {
        "$type": "oid",
        "$value": "57c5be1de4b0524ca3cb7a14"
      },
      "recommendation": {
        "table_name": "T_MEDD_PUF_PHMCY_NTWRK"
      }
    },
    {
      "entity_type": "table",
      "entity_id": {
        "$type": "oid",
        "$value": "57c5be1de4b0524ca3cb7a19"
      },
      "recommendation": {
        "table_name": "T_MEDD_PUF_PLAN"
      }
    },
    {
      "entity_type": "table",
      "entity_id": {
        "$type": "oid",
        "$value": "57c5be1de4b0524ca3cb7a1e"
      },
      "recommendation": {
        "table_name": "T_PDE_BTCH_HDR_TRLR_DTL"
      }
    },
    {
      "entity_type": "table",
      "entity_id": {
        "$type": "oid",
        "$value": "57c5be1de4b0524ca3cb7a23"
      },
      "recommendation": {
        "table_name": "T_PDE_DTL"
      }
    },
    {
      "entity_type": "table",
      "entity_id": {
        "$type": "oid",
        "$value": "57c5be1de4b0524ca3cb7a28"
      },
      "recommendation": {
        "table_name": "T_PDE_RTRCT"
      }
    },
    {
      "entity_type": "table",
      "entity_id": {
        "$type": "oid",
        "$value": "57c5be1de4b0524ca3cb7a2d"
      },
      "recommendation": {
        "table_name": "T_PHMCY_CLM"
      }
    },
    {
      "entity_type": "table",
      "entity_id": {
        "$type": "oid",
        "$value": "57c5be1de4b0524ca3cb7a32"
      },
      "recommendation": {
        "table_name": "T_PHMCY_CLM_ENTPR_TF_TOC"
      }
    },
    {
      "entity_type": "table",
      "entity_id": {
        "$type": "oid",
        "$value": "57c5be1de4b0524ca3cb7a37"
      },
      "recommendation": {
        "table_name": "T_PHMCY_CLM_TF_LTR_MAIL_DT"
      }
    },
    {
      "entity_type": "table",
      "entity_id": {
        "$type": "oid",
        "$value": "57c5be1de4b0524ca3cb7a3c"
      },
      "recommendation": {
        "table_name": "T_PHMCY_HIST"
      }
    },
    {
      "entity_type": "table",
      "entity_id": {
        "$type": "oid",
        "$value": "57c5be1de4b0524ca3cb7a41"
      },
      "recommendation": {
        "table_name": "T_PROD"
      }
    },
    {
      "entity_type": "table",
      "entity_id": {
        "$type": "oid",
        "$value": "57c5be1de4b0524ca3cb7a46"
      },
      "recommendation": {
        "table_name": "T_PRSCBR_FCLTY_HIST"
      }
    },
    {
      "entity_type": "table",
      "entity_id": {
        "$type": "oid",
        "$value": "57c5be1de4b0524ca3cb7a4b"
      },
      "recommendation": {
        "table_name": "T_PRSCBR_ST_LIC"
      }
    },
    {
      "entity_type": "table",
      "entity_id": {
        "$type": "oid",
        "$value": "57c5be1de4b0524ca3cb7a50"
      },
      "recommendation": {
        "table_name": "T_REC_HIST"
      }
    },
    {
      "entity_type": "table",
      "entity_id": {
        "$type": "oid",
        "$value": "57c5be1de4b0524ca3cb7a55"
      },
      "recommendation": {
        "table_name": "T_RXC_PRIOR_ATHZN"
      }
    },
    {
      "entity_type": "table",
      "entity_id": {
        "$type": "oid",
        "$value": "57c5be1de4b0524ca3cb7a5a"
      },
      "recommendation": {
        "table_name": "T_SPEC_DRUG"
      }
    },
    {
      "entity_type": "table",
      "entity_id": {
        "$type": "oid",
        "$value": "57c5be1de4b0524ca3cb7a5f"
      },
      "recommendation": {
        "table_name": "T_USRVW_CLNT_LST"
      }
    },
    {
      "entity_type": "table",
      "entity_id": {
        "$type": "oid",
        "$value": "57c5be1de4b0524ca3cb7a64"
      },
      "recommendation": {
        "table_name": "T_ZIP5"
      }
    },
    {
      "entity_type": "table",
      "entity_id": {
        "$type": "oid",
        "$value": "57c5be1be4b0524ca3cb787a"
      },
      "recommendation": {
        "table_name": "big_table_one_ET"
      }
    },
    {
      "entity_type": "table",
      "entity_id": {
        "$type": "oid",
        "$value": "57c5be1be4b0524ca3cb787f"
      },
      "recommendation": {
        "table_name": "big_table_one_Log"
      }
    },
    {
      "entity_type": "table",
      "entity_id": {
        "$type": "oid",
        "$value": "57c5be1be4b0524ca3cb7884"
      },
      "recommendation": {
        "table_name": "big_table_one_UV"
      }
    },
    {
      "entity_type": "table",
      "entity_id": {
        "$type": "oid",
        "$value": "57c5be1be4b0524ca3cb7889"
      },
      "recommendation": {
        "table_name": "big_table_one_WT"
      }
    },
    {
      "entity_type": "table",
      "entity_id": {
        "$type": "oid",
        "$value": "57c5be1be4b0524ca3cb788e"
      },
      "recommendation": {
        "table_name": "blob_unicode"
      }
    },
    {
      "entity_type": "table",
      "entity_id": {
        "$type": "oid",
        "$value": "57c5be1be4b0524ca3cb7898"
      },
      "recommendation": {
        "table_name": "cat_one_demo_test"
      }
    },
    {
      "entity_type": "table",
      "entity_id": {
        "$type": "oid",
        "$value": "57c5be1be4b0524ca3cb78a2"
      },
      "recommendation": {
        "table_name": "cat_one_test_new"
      }
    },
    {
      "entity_type": "table",
      "entity_id": {
        "$type": "oid",
        "$value": "57c5be1be4b0524ca3cb78ac"
      },
      "recommendation": {
        "table_name": "cat_two_scd1_both"
      }
    },
    {
      "entity_type": "table",
      "entity_id": {
        "$type": "oid",
        "$value": "57c5be1be4b0524ca3cb78bb"
      },
      "recommendation": {
        "table_name": "customer_success"
      }
    },
    {
      "entity_type": "table",
      "entity_id": {
        "$type": "oid",
        "$value": "57c5be1be4b0524ca3cb78c0"
      },
      "recommendation": {
        "table_name": "full_export"
      }
    },
    {
      "entity_type": "table",
      "entity_id": {
        "$type": "oid",
        "$value": "57c5be1be4b0524ca3cb78c5"
      },
      "recommendation": {
        "table_name": "incr_export"
      }
    },
    {
      "entity_type": "table",
      "entity_id": {
        "$type": "oid",
        "$value": "57c5be1be4b0524ca3cb78cf"
      },
      "recommendation": {
        "table_name": "schema_change_test"
      }
    },
    {
      "entity_type": "table",
      "entity_id": {
        "$type": "oid",
        "$value": "57c5be1be4b0524ca3cb78d4"
      },
      "recommendation": {
        "table_name": "special_case_test"
      }
    },
    {
      "entity_type": "table",
      "entity_id": {
        "$type": "oid",
        "$value": "57c5be1be4b0524ca3cb78d9"
      },
      "recommendation": {
        "table_name": "splchars"
      }
    },
    {
      "entity_type": "table",
      "entity_id": {
        "$type": "oid",
        "$value": "57c5be1be4b0524ca3cb78e3"
      },
      "recommendation": {
        "table_name": "temp_customer_success"
      }
    },
    {
      "entity_type": "table",
      "entity_id": {
        "$type": "oid",
        "$value": "57c5be1be4b0524ca3cb78ed"
      },
      "recommendation": {
        "table_name": "testJoin"
      }
    },
    {
      "entity_type": "table",
      "entity_id": {
        "$type": "oid",
        "$value": "57c5be1be4b0524ca3cb78fc"
      },
      "recommendation": {
        "table_name": "testTPT"
      }
    },
    {
      "entity_type": "table",
      "entity_id": {
        "$type": "oid",
        "$value": "57c5be1be4b0524ca3cb7901"
      },
      "recommendation": {
        "table_name": "test_dattypes_numeric"
      }
    },
    {
      "entity_type": "table",
      "entity_id": {
        "$type": "oid",
        "$value": "57c5be1ce4b0524ca3cb7906"
      },
      "recommendation": {
        "table_name": "test_delim_escape_tbl"
      }
    },
    {
      "entity_type": "table",
      "entity_id": {
        "$type": "oid",
        "$value": "57c5be1ce4b0524ca3cb790b"
      },
      "recommendation": {
        "table_name": "test_schema"
      }
    },
    {
      "entity_type": "table",
      "entity_id": {
        "$type": "oid",
        "$value": "57c5be1be4b0524ca3cb78f2"
      },
      "recommendation": {
        "table_name": "testtable2"
      }
    },
    {
      "entity_type": "table",
      "entity_id": {
        "$type": "oid",
        "$value": "57c5be1be4b0524ca3cb78f7"
      },
      "recommendation": {
        "table_name": "testtable3"
      }
    },
    {
      "entity_type": "table",
      "entity_id": {
        "$type": "oid",
        "$value": "57c5be1ce4b0524ca3cb7910"
      },
      "recommendation": {
        "table_name": "tpt_keywords"
      }
    },
    {
      "entity_type": "table",
      "entity_id": {
        "$type": "oid",
        "$value": "57c5be1ce4b0524ca3cb7915"
      },
      "recommendation": {
        "table_name": "twocols"
      }
    },
    {
      "entity_type": "table",
      "entity_id": {
        "$type": "oid",
        "$value": "57c5be1de4b0524ca3cb7a69"
      },
      "recommendation": {
        "table_name": "unicode_test"
      }
    },
    {
      "entity_type": "table",
      "entity_id": {
        "$type": "oid",
        "$value": "57c5be1de4b0524ca3cb7a6e"
      },
      "recommendation": {
        "table_name": "utillog1"
      }
    },
    {
      "entity_type": "table",
      "entity_id": {
        "$type": "oid",
        "$value": "57c5be1de4b0524ca3cb7a73"
      },
      "recommendation": {
        "table_name": "utillog2"
      }
    },
    {
      "entity_type": "table",
      "entity_id": {
        "$type": "oid",
        "$value": "57c5be1de4b0524ca3cb7a78"
      },
      "recommendation": {
        "table_name": "utillog6"
      }
    },
    {
      "entity_type": "table",
      "entity_id": {
        "$type": "oid",
        "$value": "57c5be1de4b0524ca3cb7a7d"
      },
      "recommendation": {
        "table_name": "vw_1_cat_one_test"
      }
    },
    {
      "entity_type": "table",
      "entity_id": {
        "$type": "oid",
        "$value": "57c5be1de4b0524ca3cb7a82"
      },
      "recommendation": {
        "table_name": "vw_cat_one_test"
      }
    },
    {
      "entity_type": "table_group",
      "entity_id": {
        "$type": "oid",
        "$value": "d6ab257953a9ec04ad6813f3"
      },
      "recommendation": {
        "table_group_name": "all"
      }
    }
  ],
  "export": {
    "exportedAt": {
      "$date": 1473310838569
    },
    "exportedBy": "Infoworks Admin"
  }
}
